local_whisper_korean_subtitle_generator/__init__.py
local_whisper_korean_subtitle_generator/tools/__init__.py
local_whisper_korean_subtitle_generator/tools/korean_translation_tool.py
local_whisper_korean_subtitle_generator/tools/srt_formatter_tool.py
local_whisper_korean_subtitle_generator/tools/whisper_json_reader_tool.py
srt_generator/__init__.py
srt_generator/cli.py
srt_generator/gui_app.py
srt_generator/gui_impl.py
ch_srtgen-1.0.9.dist-info/METADATA
ch_srtgen-1.0.9.dist-info/WHEEL
ch_srtgen-1.0.9.dist-info/entry_points.txt
ch_srtgen-1.0.9.dist-info/top_level.txt
ch_srtgen-1.0.9.dist-info/RECORD
